llama_voice/__init__.py
llama_voice/config.py
llama_voice/core.py
llama_voice/models/__init__.py
llama_voice/processor/__init__.py
llama_voice/processor/anonymizer.py
llama_voice/processor/asr_processor.py
llama_voice/processor/feature_extractor.py
llama_voice/processor/intent_handler.py
llama_voice/processor/prosody_analyzer.py
llama_voice/processor/secure_enclave.py
llama_voice/processor/text_repair.py
llama_voice/processor/voice_processor_pipeline.py
llama_voice/processor/watermark_detector.py
llama_voice/utils/__init__.py
llama_voice/utils/audio_utils.py
llama_voice-0.1.0.dist-info/licenses/LICENSE
llama_voice-0.1.0.dist-info/METADATA
llama_voice-0.1.0.dist-info/WHEEL
llama_voice-0.1.0.dist-info/top_level.txt
llama_voice-0.1.0.dist-info/RECORD
